{"version":1,"resource":"file:///mnt/shared/projects/code/js/p5/system-prototype/src/sprites.js","entries":[{"id":"19md.js","timestamp":1699200578072},{"id":"b1b0.js","timestamp":1699200628617},{"id":"Lkg2.js","timestamp":1699200656651},{"id":"8bso.js","timestamp":1699200673393},{"id":"lzPA.js","timestamp":1699200688380},{"id":"XbLP.js","timestamp":1699200720345},{"id":"0U6N.js","timestamp":1699200753536},{"id":"M8s5.js","timestamp":1699200812209},{"id":"iGtp.js","timestamp":1699200835480},{"id":"mUue.js","timestamp":1699200859898},{"id":"3QK1.js","timestamp":1699201021273},{"id":"V05m.js","timestamp":1699201265212},{"id":"H976.js","timestamp":1699201328682},{"id":"9ZKt.js","timestamp":1699205445890},{"id":"jMfa.js","timestamp":1699205798484},{"id":"Lkp6.js","timestamp":1699205980144}]}